README
setup.py
src/carp.py
src/carp.egg-info/PKG-INFO
src/carp.egg-info/SOURCES.txt
src/carp.egg-info/dependency_links.txt
src/carp.egg-info/entry_points.txt
src/carp.egg-info/requires.txt
src/carp.egg-info/top_level.txt