Metadata-Version: 1.0
Name: carp
Version: 0.0.3
Summary: Code templating scripts
Home-page: http://carp.readthedocs.org
Author: W. Matthew Wilson
Author-email: matt@tplus1.com
License: BSD
Platform: UNKNOWN
